dbus_networkdevices/__init__.py
dbus_networkdevices/__main__.py
dbus_networkdevices-2024.7.0.dist-info/LICENSE.md
dbus_networkdevices-2024.7.0.dist-info/METADATA
dbus_networkdevices-2024.7.0.dist-info/WHEEL
dbus_networkdevices-2024.7.0.dist-info/entry_points.txt
dbus_networkdevices-2024.7.0.dist-info/top_level.txt
dbus_networkdevices-2024.7.0.dist-info/RECORD
