Metadata-Version: 2.1
Name: dbus_networkdevices
Version: 2024.7.0
Summary: Connected network devices using DBus
Author-email: bkbilly <bkbilly@hotmail.com>
Project-URL: Source Code, https://github.com/bkbilly/dbus_networkdevices
Keywords: dbus,ip,network
Classifier: Programming Language :: Python :: 3
Classifier: License :: OSI Approved :: MIT License
Classifier: Operating System :: Unix
Requires-Python: >=3.7.0
License-File: LICENSE.md
Requires-Dist: dasbus >=1.7
Requires-Dist: PyGObject >=3.44.0
